pytest_continuous/__init__.py
pytest_continuous/plugin.py
pytest_continuous-0.1.3.dist-info/METADATA
pytest_continuous-0.1.3.dist-info/WHEEL
pytest_continuous-0.1.3.dist-info/entry_points.txt
pytest_continuous-0.1.3.dist-info/top_level.txt
pytest_continuous-0.1.3.dist-info/RECORD
